setup.py
Dutch_Document_Validator.egg-info/PKG-INFO
Dutch_Document_Validator.egg-info/SOURCES.txt
Dutch_Document_Validator.egg-info/dependency_links.txt
Dutch_Document_Validator.egg-info/top_level.txt
modules/__init__.py
modules/bsn.py
modules/passport.py