Metadata-Version: 1.1
Name: Dutch-Document-Validator
Version: 0.0.1
Summary: A basic ducth document validator
Home-page: UNKNOWN
Author: Ankit Gupta
Author-email: devankitgupta01@gmail.com
License: MIT
Keywords: dutch document validator
Platform: UNKNOWN
Classifier: Development Status :: 5 - Production/Stable
Classifier: Operating System :: Microsoft :: Windows :: Windows 10
Classifier: License :: OSI Approved :: MIT License
Classifier: Programming Language :: Python :: 3
